{"type":"FeatureCollection","features":[{"type":"Feature","id":2,"geometry":{"type":"Point","coordinates":[-3.1842575138820113,55.947014922881905]},"properties":{"OBJECTID":2,"Name":"University of Edinburgh","Degree":"MSc GIS","Start":2022,"End":2023}},{"type":"Feature","id":3,"geometry":{"type":"Point","coordinates":[-3.3214554204764921,55.911828713834723]},"properties":{"OBJECTID":3,"Name":"Heriot-Watt University","Degree":"MSc MRDP","Start":2015,"End":2016}},{"type":"Feature","id":4,"geometry":{"type":"Point","coordinates":[151.11319859286002,-33.775347260191673]},"properties":{"OBJECTID":4,"Name":"Macquarie University","Degree":"BA","Start":2012,"End":2015}},{"type":"Feature","id":5,"geometry":{"type":"Point","coordinates":[1.0936418926500795,51.26973656825767]},"properties":{"OBJECTID":5,"Name":"CATS Canterbury","Degree":"International Baccalaureate","Start":2009,"End":2011}}]}